{"code":200,"event":"BOT EVENT","initiator":"nest-informer-bot#2730","level":"info","message":"Going online ","timestamp":"05 May 10:56:44.84"},
{"code":200,"event":"BOT EVENT","initiator":"nest-informer-bot#2730","level":"info","message":"Going online ","timestamp":"05 May 10:57:48.70"},
{"code":200,"event":"BOT EVENT","initiator":"nest-informer-bot#2730","level":"info","message":"Going online ","timestamp":"05 May 10:59:38.32"},
{"code":200,"event":"BOT EVENT","initiator":"nest-informer-bot#2730","level":"info","message":"Going online ","timestamp":"05 May 11:43:34.88"},
{"code":200,"event":"BOT EVENT","initiator":"nest-informer-bot#2730","level":"info","message":"Going online ","timestamp":"05 May 11:44:05.11"},
{"code":200,"event":"BOT EVENT","initiator":"nest-informer-bot#2730","level":"info","message":"Going online ","timestamp":"05 May 12:28:10.40"},
{"code":200,"event":"BOT EVENT","initiator":"nest-informer-bot#2730","level":"info","message":"Going online ","timestamp":"05 May 13:20:54.09"},
